demure_captcha/__init__.py
demure_captcha/__main__.py
demure_captcha/captcha.py
demure_captcha/char.py
demure_captcha/phrase.py
demure_captcha/speaker.py
demure_captcha/themes.py
demure_captcha/fonts/__init__.py
demure_captcha/fonts/files/berd-bold.otf
demure_captcha/fonts/files/butler-bold.otf
demure_captcha/fonts/files/butler-bold_stencil.otf
demure_captcha/fonts/files/butler-extra_bold.otf
demure_captcha/fonts/files/butler-extra_bold_stencil.otf
demure_captcha/fonts/files/butler-light.otf
demure_captcha/fonts/files/butler-light_stencil.otf
demure_captcha/fonts/files/butler-medium.otf
demure_captcha/fonts/files/butler-medium_stencil.otf
demure_captcha/fonts/files/butler-regular.otf
demure_captcha/fonts/files/butler-regular_stencil.otf
demure_captcha/fonts/files/butler-thin.otf
demure_captcha/fonts/files/butler-ultra_light_stencil.otf
demure_captcha/fonts/files/butler.otf
demure_captcha/fonts/files/butlet-stencil.otf
demure_captcha/fonts/files/maghfirea.otf
demure_captcha/fonts/files/mangabey-regular.otf
demure_captcha-0.8.2.data/data/fonts/files/berd-bold.otf
demure_captcha-0.8.2.data/data/fonts/files/butler-bold.otf
demure_captcha-0.8.2.data/data/fonts/files/butler-bold_stencil.otf
demure_captcha-0.8.2.data/data/fonts/files/butler-extra_bold.otf
demure_captcha-0.8.2.data/data/fonts/files/butler-extra_bold_stencil.otf
demure_captcha-0.8.2.data/data/fonts/files/butler-light.otf
demure_captcha-0.8.2.data/data/fonts/files/butler-light_stencil.otf
demure_captcha-0.8.2.data/data/fonts/files/butler-medium.otf
demure_captcha-0.8.2.data/data/fonts/files/butler-medium_stencil.otf
demure_captcha-0.8.2.data/data/fonts/files/butler-regular.otf
demure_captcha-0.8.2.data/data/fonts/files/butler-regular_stencil.otf
demure_captcha-0.8.2.data/data/fonts/files/butler-thin.otf
demure_captcha-0.8.2.data/data/fonts/files/butler-ultra_light_stencil.otf
demure_captcha-0.8.2.data/data/fonts/files/butler.otf
demure_captcha-0.8.2.data/data/fonts/files/butlet-stencil.otf
demure_captcha-0.8.2.dist-info/LICENSE.txt
demure_captcha-0.8.2.dist-info/METADATA
demure_captcha-0.8.2.dist-info/WHEEL
demure_captcha-0.8.2.dist-info/top_level.txt
demure_captcha-0.8.2.dist-info/RECORD
