Metadata-Version: 2.1
Name: demure-captcha
Version: 0.8.2
Summary: Simple but customize captcha generator( image + voice )
Home-page: https://github.com/grdvsng/demure_captcha
Author: Trishkin Sergey
Author-email: grdvsng@gmail.com
License: UNKNOWN
Platform: UNKNOWN
Classifier: Programming Language :: Python :: 3.8
Classifier: License :: OSI Approved :: GNU General Public License v3 or later (GPLv3+)
Requires-Python: >=3.8
License-File: LICENSE.txt
Requires-Dist: atomicwrites (>=1.4.0)
Requires-Dist: attrs (>=21.4.0)
Requires-Dist: colorama (>=0.4.4)
Requires-Dist: comtypes (>=1.1.11)
Requires-Dist: iniconfig (>=1.1.1)
Requires-Dist: packaging (>=21.3)
Requires-Dist: Pillow (>=9.1.0)
Requires-Dist: pluggy (>=1.0.0)
Requires-Dist: py (>=1.11.0)
Requires-Dist: pydantic (>=1.9.0)
Requires-Dist: pyparsing (>=3.0.7)
Requires-Dist: pypiwin32 (>=223)
Requires-Dist: pytest (>=7.1.1)
Requires-Dist: pyttsx3 (>=2.90)
Requires-Dist: pywin32 (>=303)
Requires-Dist: tomli (>=2.0.1)
Requires-Dist: typing-extensions (>=4.1.1)
